<record><leader>01248cz  a2200277n  4500</leader><controlfield tag="005">20240725141757.0</controlfield><controlfield tag="008">020403i| anannbabn          |a ana     c</controlfield><controlfield tag="001">98187481368006381</controlfield><datafield ind1=" " ind2=" " tag="010"><subfield code="a">sh 97006426</subfield></datafield><datafield ind1=" " ind2=" " tag="035"><subfield code="a">(DLC) sh 97006426</subfield></datafield><datafield ind1=" " ind2=" " tag="035"><subfield code="a">(LIBRARY_OF_CONGRESS)98170039530000041</subfield></datafield><datafield ind1=" " ind2=" " tag="040"><subfield code="a">MnMHCL</subfield><subfield code="c">DLC</subfield><subfield code="d">WaElC</subfield><subfield code="d">MiU</subfield></datafield><datafield ind1=" " ind2=" " tag="150"><subfield code="a">Immigrant detention centers</subfield></datafield><datafield ind1=" " ind2=" " tag="450"><subfield code="w">nne</subfield><subfield code="a">Alien detention centers</subfield></datafield><datafield ind1=" " ind2=" " tag="450"><subfield code="a">Detention centers, Alien</subfield></datafield><datafield ind1=" " ind2=" " tag="450"><subfield code="a">Detention centers, Noncitizen</subfield></datafield><datafield ind1=" " ind2=" " tag="450"><subfield code="a">Detention centers, Immigration</subfield></datafield><datafield ind1=" " ind2=" " tag="450"><subfield code="a">Immigration detention centers</subfield></datafield><datafield ind1=" " ind2=" " tag="450"><subfield code="a">Undocumented immigrant detention centers</subfield></datafield><datafield ind1=" " ind2=" " tag="550"><subfield code="w">g</subfield><subfield code="a">Detention of persons</subfield></datafield><datafield ind1=" " ind2=" " tag="550"><subfield code="a">Noncitizen detention centers</subfield></datafield><datafield ind1=" " ind2=" " tag="550"><subfield code="a">Illegal immigration</subfield></datafield><datafield ind1=" " ind2=" " tag="670"><subfield code="a">LC database, Sept. 8, 1997</subfield><subfield code="b">(Oakdale Federal Alien Detention Center)</subfield></datafield><datafield ind1=" " ind2=" " tag="670"><subfield code="a">WWW, Sept. 8, 1997</subfield><subfield code="b">(alien detention centers)</subfield></datafield><datafield ind1=" " ind2=" " tag="690"><subfield code="a">sla-lab updated based on DEIA Catalog Working Group changes May 2021; "Undocumented immigrants" term borrowed from Sears ; "undocumented foreign national" term from Bill H.R. 3776 (116th Congress); "noncitizen" term from Bill H.R.1177 (117th Congress)</subfield></datafield><datafield ind1=" " ind2=" " tag="690"><subfield code="a">sla-lab updated to include 550s for LCSH headings as references March 2023</subfield></datafield></record>
<record><leader>01299cz  a2200313n  4500</leader><controlfield tag="005">20240725142627.0</controlfield><controlfield tag="008">030627i| anannbabn          |a ana      </controlfield><controlfield tag="001">98187481368106381</controlfield><datafield ind1=" " ind2=" " tag="010"><subfield code="a">sh 85003553</subfield></datafield><datafield ind1=" " ind2=" " tag="035"><subfield code="a">(DLC)sh 85003553</subfield></datafield><datafield ind1=" " ind2=" " tag="035"><subfield code="a">(LIBRARY_OF_CONGRESS)98171057700000041</subfield></datafield><datafield ind1=" " ind2=" " tag="040"><subfield code="a">DLC</subfield><subfield code="c">DLC</subfield><subfield code="d">DLC</subfield><subfield code="d">WaU</subfield></datafield><datafield ind1=" " ind2=" " tag="150"><subfield code="a">Undocumented immigrants</subfield></datafield><datafield ind1=" " ind2=" " tag="450"><subfield code="a">Undocumented foreign nationals</subfield></datafield><datafield ind1=" " ind2=" " tag="450"><subfield code="w">nne</subfield><subfield code="a">Illegal aliens</subfield></datafield><datafield ind1=" " ind2=" " tag="450"><subfield code="a">Aliens</subfield><subfield code="x">Legal status, laws, etc.</subfield></datafield><datafield ind1=" " ind2=" " tag="450"><subfield code="w">nne</subfield><subfield code="a">Aliens, Illegal</subfield></datafield><datafield ind1=" " ind2=" " tag="450"><subfield code="a">Illegal aliens</subfield><subfield code="x">Legal status, laws, etc.</subfield></datafield><datafield ind1=" " ind2=" " tag="450"><subfield code="a">Illegal immigrants</subfield></datafield><datafield ind1=" " ind2=" " tag="450"><subfield code="a">Undocumented noncitizens</subfield></datafield><datafield ind1=" " ind2=" " tag="550"><subfield code="w">g</subfield><subfield code="a">Noncitizens</subfield></datafield><datafield ind1=" " ind2=" " tag="550"><subfield code="a">Immigrant detention centers</subfield></datafield><datafield ind1=" " ind2=" " tag="550"><subfield code="a">Human smuggling</subfield></datafield><datafield ind1=" " ind2=" " tag="550"><subfield code="a">Noncitizens</subfield></datafield><datafield ind1=" " ind2=" " tag="550"><subfield code="a">Illegal immigration</subfield></datafield><datafield ind1=" " ind2=" " tag="670"><subfield code="a">Work cat.: 2007017970: Illegal immigration, 2007:</subfield><subfield code="b">eCIP data sheet (Illegal immigrants)</subfield></datafield><datafield ind1=" " ind2=" " tag="690"><subfield code="a">sla-lab updated based on DEIA Catalog Working Group changes May 2021; "Undocumented immigrants" term borrowed from Sears ; "undocumented foreign national" term from Bill H.R. 3776 (116th Congress)</subfield></datafield><datafield ind1=" " ind2=" " tag="690"><subfield code="a">sla-lab updated to include 550s for LCSH headings as references March 2023</subfield></datafield><datafield ind1=" " ind2=" " tag="690"><subfield code="a">sla-lab updated 550 broader term from "Aliens" to "Noncitizens" May 2024</subfield></datafield></record>
<record><leader>01310nz  a2200265n  4500</leader><controlfield tag="005">20240725141738.0</controlfield><controlfield tag="008">110225i| anannbabn          |a ana     c</controlfield><controlfield tag="001">98187481368206381</controlfield><datafield ind1=" " ind2=" " tag="010"><subfield code="a">sh2011000897</subfield></datafield><datafield ind1=" " ind2=" " tag="035"><subfield code="a">(DLC)sh2011000897</subfield></datafield><datafield ind1=" " ind2=" " tag="035"><subfield code="a">(LIBRARY_OF_CONGRESS)98174486310000041</subfield></datafield><datafield ind1=" " ind2=" " tag="040"><subfield code="a">MdBmJHUP</subfield><subfield code="b">eng</subfield><subfield code="c">DLC</subfield><subfield code="d">MiU</subfield></datafield><datafield ind1=" " ind2=" " tag="150"><subfield code="a">Children of undocumented immigrants</subfield></datafield><datafield ind1=" " ind2=" " tag="450"><subfield code="a">Children of undocumented foreign nationals</subfield></datafield><datafield ind1=" " ind2=" " tag="450"><subfield code="w">nne</subfield><subfield code="a">Children of illegal aliens</subfield></datafield><datafield ind1=" " ind2=" " tag="450"><subfield code="a">First generation children</subfield></datafield><datafield ind1=" " ind2=" " tag="450"><subfield code="a">Illegal aliens' children</subfield></datafield><datafield ind1=" " ind2=" " tag="450"><subfield code="a">Second generation children</subfield></datafield><datafield ind1=" " ind2=" " tag="450"><subfield code="a">Noncitizens' children</subfield></datafield><datafield ind1=" " ind2=" " tag="550"><subfield code="w">g</subfield><subfield code="a">Undocumented immigrants</subfield></datafield><datafield ind1=" " ind2=" " tag="550"><subfield code="a">Children of noncitizens</subfield></datafield><datafield ind1=" " ind2=" " tag="670"><subfield code="a">Work cat.: Journal of Health Care for the Poor and Underserved, 2010:</subfield><subfield code="b">v. 21, no. 3, p. 809 (Zayas, Luis Herminio. Protecting Citizen-Children Safeguards Our Common Future)</subfield></datafield><datafield ind1=" " ind2=" " tag="670"><subfield code="a">U.S. News.com WWW site, Mar. 5, 2011</subfield><subfield code="b">(Children of illegal aliens, should they be U.S. citizens)</subfield></datafield><datafield ind1=" " ind2=" " tag="690"><subfield code="a">a sla-lab updated based on DEIA Catalog Working Group changes May 2021; "Undocumented immigrants" term borrowed from Sears ; "undocumented foreign national" term from Bill H.R. 3776 (116th Congress)</subfield></datafield><datafield ind1=" " ind2=" " tag="690"><subfield code="a">sla-lab updated to include 550s for LCSH headings as references March 2023</subfield></datafield></record>
<record><leader>00838nz  a2200181n  4500</leader><controlfield tag="005">20240725141724.0</controlfield><controlfield tag="008">110711|| anannbabn          |n ana      </controlfield><controlfield tag="001">98187481368306381</controlfield><datafield ind1=" " ind2=" " tag="010"><subfield code="a">sh2011003415</subfield></datafield><datafield ind1=" " ind2=" " tag="035"><subfield code="a">(DLC)sh2011003415</subfield></datafield><datafield ind1=" " ind2=" " tag="035"><subfield code="a">(LIBRARY_OF_CONGRESS)98176431160000041</subfield></datafield><datafield ind1=" " ind2=" " tag="040"><subfield code="a">DLC</subfield><subfield code="b">eng</subfield><subfield code="c">DLC</subfield><subfield code="d">MiU</subfield></datafield><datafield ind1=" " ind2=" " tag="150"><subfield code="a">Children of undocumented immigrants</subfield><subfield code="x">Education</subfield></datafield><datafield ind1=" " ind2=" " tag="450"><subfield code="a">Children of undocumented foreign nationals</subfield><subfield code="x">Education</subfield></datafield><datafield ind1=" " ind2=" " tag="450"><subfield code="w">nne</subfield><subfield code="a">Children of illegal aliens</subfield><subfield code="x">Education</subfield></datafield><datafield ind1=" " ind2=" " tag="550"><subfield code="a">Children of noncitizens</subfield><subfield code="x">Education</subfield></datafield><datafield ind1=" " ind2=" " tag="690"><subfield code="a">sla-lab updated based on DEIA Catalog Working Group changes May 2021; "Undocumented immigrants" term borrowed from Sears ; "undocumented foreign national" term from Bill H.R. 3776 (116th Congress)</subfield></datafield><datafield ind1=" " ind2=" " tag="690"><subfield code="a">sla-lab updated to include 550s for LCSH headings as references March 2023</subfield></datafield></record>
<record><leader>01075nz  a2200205n  4500</leader><controlfield tag="005">20240725141702.0</controlfield><controlfield tag="008">110701i| anannbabn          |a ana      </controlfield><controlfield tag="001">98187481368406381</controlfield><datafield ind1=" " ind2=" " tag="010"><subfield code="a">sh2011003293</subfield></datafield><datafield ind1=" " ind2=" " tag="035"><subfield code="a">(DLC)sh2011003293</subfield></datafield><datafield ind1=" " ind2=" " tag="035"><subfield code="a">(LIBRARY_OF_CONGRESS)98176413560000041</subfield></datafield><datafield ind1=" " ind2=" " tag="040"><subfield code="a">DLC</subfield><subfield code="b">eng</subfield><subfield code="c">DLC</subfield><subfield code="d">MiU</subfield></datafield><datafield ind1=" " ind2=" " tag="150"><subfield code="a">Children of undocumented immigrants</subfield><subfield code="x">Education</subfield><subfield code="x">Law and legislation</subfield></datafield><datafield ind1=" " ind2=" " tag="450"><subfield code="a">Children of undocumented foreign nationals</subfield><subfield code="x">Education</subfield><subfield code="x">Law and legislation</subfield></datafield><datafield ind1=" " ind2=" " tag="450"><subfield code="w">nne</subfield><subfield code="a">Children of illegal aliens</subfield><subfield code="x">Education</subfield><subfield code="x">Law and legislation</subfield></datafield><datafield ind1=" " ind2=" " tag="550"><subfield code="w">g</subfield><subfield code="a">Educational law and legislation</subfield></datafield><datafield ind1=" " ind2=" " tag="550"><subfield code="a">Children of noncitizens</subfield><subfield code="x">Education</subfield><subfield code="x">Law and legislation</subfield></datafield><datafield ind1=" " ind2=" " tag="670"><subfield code="a">Work cat.: 2011028194: Olivas, Michael A. No undocumented child left behind, c2011.</subfield></datafield><datafield ind1=" " ind2=" " tag="690"><subfield code="a">a sla-lab updated based on DEIA Catalog Working Group changes May 2021; "Undocumented immigrants" term borrowed from Sears ; "undocumented foreign national" term from Bill H.R. 3776 (116th Congress)</subfield></datafield><datafield ind1=" " ind2=" " tag="690"><subfield code="a">sla-lab updated to include 550s for LCSH headings as references March 2023</subfield></datafield></record>
<record><leader>00995nz  a2200205n  4500</leader><controlfield tag="005">20240725142606.0</controlfield><controlfield tag="008">080211|| anannbabn          |n ana      </controlfield><controlfield tag="001">98187481368506381</controlfield><datafield ind1=" " ind2=" " tag="010"><subfield code="a">sh2008104250</subfield></datafield><datafield ind1=" " ind2=" " tag="035"><subfield code="a">(DLC) sh2008104250</subfield></datafield><datafield ind1=" " ind2=" " tag="035"><subfield code="a">(LIBRARY_OF_CONGRESS)98170331580000041</subfield></datafield><datafield ind1=" " ind2=" " tag="040"><subfield code="a">DLC</subfield><subfield code="b">eng</subfield><subfield code="c">DLC</subfield><subfield code="d">MiU</subfield></datafield><datafield ind1=" " ind2=" " tag="150"><subfield code="a">Undocumented immigrants</subfield><subfield code="x">Government policy</subfield><subfield code="z">United States</subfield></datafield><datafield ind1=" " ind2=" " tag="450"><subfield code="a">Undocumented foreign nationals</subfield><subfield code="x">Government policy</subfield><subfield code="z">United States</subfield></datafield><datafield ind1=" " ind2=" " tag="450"><subfield code="w">nne</subfield><subfield code="a">Illegal aliens</subfield><subfield code="x">Government policy</subfield><subfield code="z">United States</subfield></datafield><datafield ind1=" " ind2=" " tag="550"><subfield code="a">Noncitizens</subfield><subfield code="x">Government policy</subfield><subfield code="z">United States</subfield></datafield><datafield ind1=" " ind2=" " tag="667"><subfield code="a">Record generated for validation purposes.</subfield></datafield><datafield ind1=" " ind2=" " tag="670"><subfield code="a">Work cat.: Illegal immigration, c2001</subfield></datafield><datafield ind1=" " ind2=" " tag="690"><subfield code="a">sla-lab updated based on DEIA Catalog Working Group changes May 2021; "Undocumented immigrants" term borrowed from Sears ; "undocumented foreign national" term from Bill H.R. 3776 (116th Congress)</subfield></datafield><datafield ind1=" " ind2=" " tag="690"><subfield code="a">sla-lab updated to include 550s for LCSH headings as references March 2023</subfield></datafield></record>
<record><leader>00919nz  a2200205n  4500</leader><controlfield tag="005">20240725142555.0</controlfield><controlfield tag="008">080211|| anannbabn          |n ana      </controlfield><controlfield tag="001">98187481368606381</controlfield><datafield ind1=" " ind2=" " tag="010"><subfield code="a">sh2008104249</subfield></datafield><datafield ind1=" " ind2=" " tag="035"><subfield code="a">(DLC) sh2008104249</subfield></datafield><datafield ind1=" " ind2=" " tag="035"><subfield code="a">(LIBRARY_OF_CONGRESS)98170331570000041</subfield></datafield><datafield ind1=" " ind2=" " tag="040"><subfield code="a">DLC</subfield><subfield code="b">eng</subfield><subfield code="c">DLC</subfield><subfield code="d">MiU</subfield></datafield><datafield ind1=" " ind2=" " tag="150"><subfield code="a">Undocumented immigrants</subfield><subfield code="z">United States</subfield></datafield><datafield ind1=" " ind2=" " tag="450"><subfield code="a">Undocumented foreign nationals</subfield><subfield code="z">United States</subfield></datafield><datafield ind1=" " ind2=" " tag="450"><subfield code="w">nne</subfield><subfield code="a">Illegal aliens</subfield><subfield code="z">United States</subfield></datafield><datafield ind1=" " ind2=" " tag="550"><subfield code="a">Noncitizens</subfield><subfield code="z">United States</subfield></datafield><datafield ind1=" " ind2=" " tag="667"><subfield code="a">Record generated for validation purposes.</subfield></datafield><datafield ind1=" " ind2=" " tag="670"><subfield code="a">Work cat.: Illegal immigration, c2001</subfield></datafield><datafield ind1=" " ind2=" " tag="690"><subfield code="a">sla-lab updated based on DEIA Catalog Working Group changes May 2021; "Undocumented immigrants" term borrowed from Sears ; "undocumented foreign national" term from Bill H.R. 3776 (116th Congress)</subfield></datafield><datafield ind1=" " ind2=" " tag="690"><subfield code="a">sla-lab updated to include 550s for LCSH headings as references March 2023</subfield></datafield></record>
<record><leader>00885nz  a2200205n  4500</leader><controlfield tag="005">20240725142453.0</controlfield><controlfield tag="008">080211|| anannbabn          |n ana      </controlfield><controlfield tag="001">98187481368706381</controlfield><datafield ind1=" " ind2=" " tag="010"><subfield code="a">sh2008104247</subfield></datafield><datafield ind1=" " ind2=" " tag="035"><subfield code="a">(DLC) sh2008104247</subfield></datafield><datafield ind1=" " ind2=" " tag="035"><subfield code="a">(LIBRARY_OF_CONGRESS)98170331550000041</subfield></datafield><datafield ind1=" " ind2=" " tag="040"><subfield code="a">DLC</subfield><subfield code="b">eng</subfield><subfield code="c">DLC</subfield><subfield code="d">MiU</subfield></datafield><datafield ind1=" " ind2=" " tag="150"><subfield code="a">Undocumented immigrants</subfield><subfield code="v">Fiction</subfield></datafield><datafield ind1=" " ind2=" " tag="450"><subfield code="a">Undocumented foreign nationals</subfield><subfield code="v">Fiction</subfield></datafield><datafield ind1=" " ind2=" " tag="450"><subfield code="w">nne</subfield><subfield code="a">Illegal aliens</subfield><subfield code="v">Fiction</subfield></datafield><datafield ind1=" " ind2=" " tag="550"><subfield code="a">Noncitizens</subfield><subfield code="v">Fiction</subfield></datafield><datafield ind1=" " ind2=" " tag="667"><subfield code="a">Record generated for validation purposes.</subfield></datafield><datafield ind1=" " ind2=" " tag="670"><subfield code="a">Work cat.: The pickup, 2001</subfield></datafield><datafield ind1=" " ind2=" " tag="690"><subfield code="a">sla-lab updated based on DEIA Catalog Working Group changes May 2021; "Undocumented immigrants" term borrowed from Sears ; "undocumented foreign national" term from Bill H.R. 3776 (116th Congress)</subfield></datafield><datafield ind1=" " ind2=" " tag="690"><subfield code="a">sla-lab updated to include 550s for LCSH headings as references March 2023</subfield></datafield></record>
<record><leader>01117cz  a2200253n  4500</leader><controlfield tag="005">20240725142641.0</controlfield><controlfield tag="008">010402i| anannbabn          |a ana      </controlfield><controlfield tag="001">98187481368806381</controlfield><datafield ind1=" " ind2=" " tag="010"><subfield code="a">sh2001002003</subfield></datafield><datafield ind1=" " ind2=" " tag="035"><subfield code="a">(DLC) sh2001002003</subfield></datafield><datafield ind1=" " ind2=" " tag="035"><subfield code="a">(LIBRARY_OF_CONGRESS)98169529040000041</subfield></datafield><datafield ind1=" " ind2=" " tag="040"><subfield code="a">DLC</subfield><subfield code="b">eng</subfield><subfield code="c">DLC</subfield><subfield code="d">MiU</subfield></datafield><datafield ind1=" " ind2=" " tag="150"><subfield code="a">Women undocumented immigrants</subfield></datafield><datafield ind1=" " ind2=" " tag="450"><subfield code="a">Women undocumented foreign nationals</subfield></datafield><datafield ind1=" " ind2=" " tag="450"><subfield code="w">nne</subfield><subfield code="a">Women illegal aliens</subfield></datafield><datafield ind1=" " ind2=" " tag="450"><subfield code="a">Undocumented women immigrants</subfield></datafield><datafield ind1=" " ind2=" " tag="450"><subfield code="a">Undocumented women aliens</subfield></datafield><datafield ind1=" " ind2=" " tag="550"><subfield code="w">g</subfield><subfield code="a">Undocumented immigrants</subfield></datafield><datafield ind1=" " ind2=" " tag="550"><subfield code="a">Women noncitizens</subfield></datafield><datafield ind1=" " ind2=" " tag="670"><subfield code="a">Work cat.: 00317281: Mujeres indocumentadas en el Perú, 1998.</subfield></datafield><datafield ind1=" " ind2=" " tag="670"><subfield code="a">LC data base, April 2, 2001</subfield><subfield code="b">(undocumented women)</subfield></datafield><datafield ind1=" " ind2=" " tag="690"><subfield code="a">sla-lab updated based on DEIA Catalog Working Group changes May 2021; "Undocumented immigrants" term borrowed from Sears ; "undocumented foreign national" term from Bill H.R. 3776 (116th Congress)</subfield></datafield><datafield ind1=" " ind2=" " tag="690"><subfield code="a">sla-lab updated to include 550s for LCSH headings as references March 2023</subfield></datafield><datafield ind1=" " ind2=" " tag="690"><subfield code="a">sla-lab updated to fix wrong 550 reference 2024-05-23</subfield></datafield></record>
<record><leader>02026cz  a2200289n  4500</leader><controlfield tag="005">20230329130712.0</controlfield><controlfield tag="008">060406i| anannbabn          |a ana     c</controlfield><controlfield tag="001">98187481368906381</controlfield><datafield ind1=" " ind2=" " tag="010"><subfield code="a">sh2002001970</subfield></datafield><datafield ind1=" " ind2=" " tag="035"><subfield code="a">(DLC) sh2002001970</subfield></datafield><datafield ind1=" " ind2=" " tag="035"><subfield code="a">(LIBRARY_OF_CONGRESS)98172020470000041</subfield></datafield><datafield ind1=" " ind2=" " tag="040"><subfield code="a">CaNSH</subfield><subfield code="b">eng</subfield><subfield code="c">DLC</subfield><subfield code="d">DLC</subfield><subfield code="d">MiU</subfield></datafield><datafield ind1=" " ind2=" " tag="150"><subfield code="a">Human smuggling</subfield></datafield><datafield ind1=" " ind2=" " tag="450"><subfield code="a">Immigrant smuggling</subfield></datafield><datafield ind1=" " ind2=" " tag="450"><subfield code="a">Migrant smuggling</subfield></datafield><datafield ind1=" " ind2=" " tag="450"><subfield code="a">People smuggling</subfield></datafield><datafield ind1=" " ind2=" " tag="550"><subfield code="w">g</subfield><subfield code="a">Smuggling</subfield></datafield><datafield ind1=" " ind2=" " tag="550"><subfield code="a">Illegal immigration</subfield></datafield><datafield ind1=" " ind2=" " tag="550"><subfield code="a">Undocumented immigrants</subfield></datafield><datafield ind1=" " ind2=" " tag="670"><subfield code="a">Work cat.: Global human smuggling: comparative perspectives, 2001.</subfield></datafield><datafield ind1=" " ind2=" " tag="670"><subfield code="a">Chin, Ko-lin. Smuggled Chinese: clandestine immigration to the United States, 1999.</subfield></datafield><datafield ind1=" " ind2=" " tag="670"><subfield code="a">Web site, European Council on  Refugees and Exiles, July 21, 2003</subfield><subfield code="b">(An overview of proposals addressing migrant smuggling and trafficking in persons: the term "trafficking" tends to describe movements of individuals against their will, whereas "smuggling" refers to voluntary movement on the part of the migrant; in the UN smuggling protocol, smuggling is defined as "... the procurement of the illegal entry into or illegal residence of a person in a State Party of which the person is not a national or a permanent resident in order to obtain, directly or indirectly, a financial or other material benefit.")</subfield></datafield><datafield ind1=" " ind2=" " tag="670"><subfield code="a">NY Times, August 13, 2003</subfield><subfield code="b">(people smugglers; immigrant smuggling)</subfield></datafield><datafield ind1=" " ind2=" " tag="670"><subfield code="a">WWW, August 13, 2003</subfield><subfield code="b">(people smuggling)</subfield></datafield><datafield ind1=" " ind2=" " tag="680"><subfield code="i">Here are entered works on facilitating the entry of illegal aliens into a country with the objective of making a profit. Works on the coercive commercial trade in human beings for the purpose of sexual or other exploitation are entered under</subfield><subfield code="a">Human trafficking.</subfield></datafield><datafield ind1=" " ind2=" " tag="681"><subfield code="i">Note under</subfield><subfield code="a">Human trafficking</subfield></datafield><datafield ind1=" " ind2=" " tag="690"><subfield code="a">sla-lab updated based on DEIA Catalog Working Group changes May 2021; "Undocumented immigrants" term borrowed from Sears ; "undocumented foreign national" term from Bill H.R. 3776 (116th Congress)</subfield></datafield></record>
<record><leader>00908cz  a2200193n  4500</leader><controlfield tag="005">20240725142615.0</controlfield><controlfield tag="008">090326 | anannbabn          |n ana      </controlfield><controlfield tag="001">98187481369006381</controlfield><datafield ind1=" " ind2=" " tag="010"><subfield code="a">sh2009001797</subfield></datafield><datafield ind1=" " ind2=" " tag="035"><subfield code="a">(DLC) sh2009001797</subfield></datafield><datafield ind1=" " ind2=" " tag="035"><subfield code="a">(LIBRARY_OF_CONGRESS)98170220560000041</subfield></datafield><datafield ind1=" " ind2=" " tag="040"><subfield code="a">DLC</subfield><subfield code="b">eng</subfield><subfield code="c">DLC</subfield><subfield code="d">MiU</subfield></datafield><datafield ind1=" " ind2=" " tag="150"><subfield code="a">Undocumented immigrants in literature</subfield></datafield><datafield ind1=" " ind2=" " tag="450"><subfield code="a">Undocumented foreign nationals in literature</subfield></datafield><datafield ind1=" " ind2=" " tag="450"><subfield code="w">nne</subfield><subfield code="a">Illegal aliens in literature</subfield></datafield><datafield ind1=" " ind2=" " tag="550"><subfield code="a">Noncitizens in literature</subfield></datafield><datafield ind1=" " ind2=" " tag="670"><subfield code="a">Work cat.: 2008485914: Clandestins dans le texte maghrébin de langue française, c2008.</subfield></datafield><datafield ind1=" " ind2=" " tag="690"><subfield code="a">sla-lab updated based on DEIA Catalog Working Group changes May 2021; "Undocumented immigrants" term borrowed from Sears ; "undocumented foreign national" term from Bill H.R. 3776 (116th Congress)</subfield></datafield><datafield ind1=" " ind2=" " tag="690"><subfield code="a">sla-lab updated to include 550s for LCSH headings as references March 2023</subfield></datafield></record>
<record><leader>01124cz  a2200253n  4500</leader><controlfield tag="005">20240725141854.0</controlfield><controlfield tag="008">080403i| anannbabn          |a ana      </controlfield><controlfield tag="001">98187481369106381</controlfield><datafield ind1=" " ind2=" " tag="010"><subfield code="a">sh2008002554</subfield></datafield><datafield ind1=" " ind2=" " tag="035"><subfield code="a">(DLC) sh2008002554</subfield></datafield><datafield ind1=" " ind2=" " tag="035"><subfield code="a">(LIBRARY_OF_CONGRESS)98171251890000041</subfield></datafield><datafield ind1=" " ind2=" " tag="040"><subfield code="a">DLC</subfield><subfield code="b">eng</subfield><subfield code="c">DLC</subfield><subfield code="d">MiU</subfield></datafield><datafield ind1=" " ind2=" " tag="150"><subfield code="a">Undocumented immigrant children</subfield></datafield><datafield ind1=" " ind2=" " tag="450"><subfield code="a">Undocumented foreign national children</subfield></datafield><datafield ind1=" " ind2=" " tag="450"><subfield code="w">nne</subfield><subfield code="a">Illegal alien children</subfield></datafield><datafield ind1=" " ind2=" " tag="450"><subfield code="a">Illegal immigrant children</subfield></datafield><datafield ind1=" " ind2=" " tag="450"><subfield code="a">Undocumented children</subfield></datafield><datafield ind1=" " ind2=" " tag="450"><subfield code="a">Undocumented child immigrants</subfield></datafield><datafield ind1=" " ind2=" " tag="450"><subfield code="a">Unaccompanied noncitizen children</subfield></datafield><datafield ind1=" " ind2=" " tag="550"><subfield code="w">g</subfield><subfield code="a">Children</subfield></datafield><datafield ind1=" " ind2=" " tag="550"><subfield code="a">Noncitizen children</subfield></datafield><datafield ind1=" " ind2=" " tag="670"><subfield code="a">Work cat.: 2008354326: A review of the public education costs of undocumented children, 2007:</subfield><subfield code="b">t.p. (Undocumented children)</subfield></datafield><datafield ind1=" " ind2=" " tag="690"><subfield code="a">sla-lab updated based on DEIA Catalog Working Group changes May 2021; "Undocumented immigrants" term borrowed from Sears ; "undocumented foreign national" term from Bill H.R. 3776 (116th Congress)</subfield></datafield><datafield ind1=" " ind2=" " tag="590"><subfield code="a">sla-lab updated to include 550s for LCSH headings as references March 2023</subfield></datafield></record>
<record><leader>00648cz  a2200157n  4500</leader><controlfield tag="005">20250225113337.0</controlfield><controlfield tag="008">100429|| anannbabn          |n ana      </controlfield><controlfield tag="001">98188860306706381</controlfield><datafield ind1=" " ind2=" " tag="010"><subfield code="a">sh2010007947</subfield></datafield><datafield ind1=" " ind2=" " tag="035"><subfield code="a">(DLC)sh2010007947</subfield></datafield><datafield ind1=" " ind2=" " tag="040"><subfield code="a">DLC</subfield><subfield code="b">eng</subfield><subfield code="c">DLC</subfield><subfield code="d">MiU</subfield></datafield><datafield ind1=" " ind2=" " tag="150"><subfield code="a">World War, 1939-1945</subfield><subfield code="x">Campaigns</subfield><subfield code="z">Mexico, Gulf of</subfield></datafield><datafield ind1=" " ind2=" " tag="450"><subfield code="a">World War, 1939-1945</subfield><subfield code="x">Campaigns</subfield><subfield code="z">America, Gulf of</subfield></datafield><datafield ind1=" " ind2=" " tag="670"><subfield code="a">Work cat.: Wiggins, Melanie. Torpedoes in the Gulf, c1995</subfield></datafield><datafield ind1=" " ind2=" " tag="690"><subfield code="a">sla-lab created local heading based on DEIA Catalog Working Group resolution to keep the term preferred by library community 2025-02-25</subfield></datafield><datafield ind1=" " ind2=" " tag="035"><subfield code="a">(LIBRARY_OF_CONGRESS)98171019720000041</subfield></datafield></record>
<record><leader>00540nz  a2200145n  4500</leader><controlfield tag="005">20250225115043.0</controlfield><controlfield tag="008">951222|| anannbab|          |n ana |||  </controlfield><controlfield tag="001">98188860306806381</controlfield><datafield ind1=" " ind2=" " tag="010"><subfield code="a">sh 95010827</subfield></datafield><datafield ind1=" " ind2=" " tag="035"><subfield code="a">(DLC) sh 95010827</subfield></datafield><datafield ind1=" " ind2=" " tag="040"><subfield code="a">DLC</subfield><subfield code="c">DLC</subfield><subfield code="d">MiU</subfield></datafield><datafield ind1=" " ind2=" " tag="150"><subfield code="a">Submarine valleys</subfield><subfield code="z">Mexico, Gulf of</subfield></datafield><datafield ind1=" " ind2=" " tag="450"><subfield code="a">Submarine valleys</subfield><subfield code="z">America, Gulf of</subfield></datafield><datafield ind1=" " ind2=" " tag="690"><subfield code="a">sla-lab created local heading based on DEIA Catalog Working Group resolution to keep the term preferred by library community 2025-02-25</subfield></datafield><datafield ind1=" " ind2=" " tag="035"><subfield code="a">(LIBRARY_OF_CONGRESS)98172603480000041</subfield></datafield></record>
<record><leader>00546nz  a2200145n  4500</leader><controlfield tag="005">20250225113247.0</controlfield><controlfield tag="008">950622|| anannbab|          |n ana |||  </controlfield><controlfield tag="001">98188860306906381</controlfield><datafield ind1=" " ind2=" " tag="010"><subfield code="a">sh 95005280</subfield></datafield><datafield ind1=" " ind2=" " tag="035"><subfield code="a">(DLC) sh 95005280</subfield></datafield><datafield ind1=" " ind2=" " tag="040"><subfield code="a">DLC</subfield><subfield code="c">DLC</subfield><subfield code="d">MiU</subfield></datafield><datafield ind1=" " ind2=" " tag="150"><subfield code="a">Submarine topography</subfield><subfield code="z">Mexico, Gulf of</subfield></datafield><datafield ind1=" " ind2=" " tag="450"><subfield code="a">Submarine topography</subfield><subfield code="z">America, Gulf of</subfield></datafield><datafield ind1=" " ind2=" " tag="690"><subfield code="a">sla-lab created local heading based on DEIA Catalog Working Group resolution to keep the term preferred by library community 2025-02-25</subfield></datafield><datafield ind1=" " ind2=" " tag="035"><subfield code="a">(LIBRARY_OF_CONGRESS)98170931400000041</subfield></datafield></record>
<record><leader>00660cz  a2200157n  4500</leader><controlfield tag="005">20250225113214.0</controlfield><controlfield tag="008">100413|| anannbabn          |n ana      </controlfield><controlfield tag="001">98188860307006381</controlfield><datafield ind1=" " ind2=" " tag="010"><subfield code="a">sh2010106426</subfield></datafield><datafield ind1=" " ind2=" " tag="035"><subfield code="a">(DLC)sh2010106426</subfield></datafield><datafield ind1=" " ind2=" " tag="040"><subfield code="a">DLC</subfield><subfield code="b">eng</subfield><subfield code="c">DLC</subfield><subfield code="d">MiU</subfield></datafield><datafield ind1=" " ind2=" " tag="150"><subfield code="a">Pilot guides</subfield><subfield code="z">Mexico, Gulf of</subfield></datafield><datafield ind1=" " ind2=" " tag="450"><subfield code="a">Pilot guides</subfield><subfield code="z">America, Gulf of</subfield></datafield><datafield ind1=" " ind2=" " tag="670"><subfield code="a">Work cat.: Derrotero de las islas Antillas, de las costas de tierra firme y de las del seno mexicano, 1980]</subfield></datafield><datafield ind1=" " ind2=" " tag="690"><subfield code="a">sla-lab created local heading based on DEIA Catalog Working Group resolution to keep the term preferred by library community 2025-02-25</subfield></datafield><datafield ind1=" " ind2=" " tag="035"><subfield code="a">(LIBRARY_OF_CONGRESS)98170526910000041</subfield></datafield></record>
<record><leader>00533cz  a2200145n  4500</leader><controlfield tag="005">20250225113154.0</controlfield><controlfield tag="008">100623|| anannbabn          |n ana      </controlfield><controlfield tag="001">98188860307106381</controlfield><datafield ind1=" " ind2=" " tag="010"><subfield code="a">sh2010011526</subfield></datafield><datafield ind1=" " ind2=" " tag="035"><subfield code="a">(DLC) sh2010011526</subfield></datafield><datafield ind1=" " ind2=" " tag="040"><subfield code="a">DLC</subfield><subfield code="b">eng</subfield><subfield code="c">DLC</subfield><subfield code="d">MiU</subfield></datafield><datafield ind1=" " ind2=" " tag="150"><subfield code="a">Oil spills</subfield><subfield code="z">Mexico, Gulf of</subfield></datafield><datafield ind1=" " ind2=" " tag="450"><subfield code="a">Oil spills</subfield><subfield code="z">America, Gulf of</subfield></datafield><datafield ind1=" " ind2=" " tag="690"><subfield code="a">sla-lab created local heading based on DEIA Catalog Working Group resolution to keep the term preferred by library community 2025-02-25</subfield></datafield><datafield ind1=" " ind2=" " tag="035"><subfield code="a">(LIBRARY_OF_CONGRESS)98171745120000041</subfield></datafield></record>
<record><leader>00660cz  a2200157n  4500</leader><controlfield tag="005">20250225113127.0</controlfield><controlfield tag="008">100317|| anannbabn          |n ana      </controlfield><controlfield tag="001">98188860307206381</controlfield><datafield ind1=" " ind2=" " tag="010"><subfield code="a">sh2010104260</subfield></datafield><datafield ind1=" " ind2=" " tag="035"><subfield code="a">(DLC)sh2010104260</subfield></datafield><datafield ind1=" " ind2=" " tag="040"><subfield code="a">DLC</subfield><subfield code="b">eng</subfield><subfield code="c">DLC</subfield><subfield code="d">MiU</subfield></datafield><datafield ind1=" " ind2=" " tag="150"><subfield code="a">Offshore oil industry</subfield><subfield code="x">Environmental aspects</subfield><subfield code="z">Mexico, Gulf of</subfield></datafield><datafield ind1=" " ind2=" " tag="450"><subfield code="a">Offshore oil industry</subfield><subfield code="x">Environmental aspects</subfield><subfield code="z">America, Gulf of</subfield></datafield><datafield ind1=" " ind2=" " tag="670"><subfield code="a">Work cat.: Environmental assessment, [2005]</subfield></datafield><datafield ind1=" " ind2=" " tag="690"><subfield code="a">sla-lab created local heading based on DEIA Catalog Working Group resolution to keep the term preferred by library community 2025-02-25</subfield></datafield><datafield ind1=" " ind2=" " tag="035"><subfield code="a">(LIBRARY_OF_CONGRESS)98168689770000041</subfield></datafield></record>
<record><leader>00540nz  a2200145n  4500</leader><controlfield tag="005">20250225113100.0</controlfield><controlfield tag="008">110428|| anannbabn          |n ana      </controlfield><controlfield tag="001">98188860307306381</controlfield><datafield ind1=" " ind2=" " tag="010"><subfield code="a">sh2011002119</subfield></datafield><datafield ind1=" " ind2=" " tag="035"><subfield code="a">(DLC)sh2011002119</subfield></datafield><datafield ind1=" " ind2=" " tag="040"><subfield code="a">DLC</subfield><subfield code="b">eng</subfield><subfield code="c">DLC</subfield><subfield code="d">MiU</subfield></datafield><datafield ind1=" " ind2=" " tag="150"><subfield code="a">Ocean currents</subfield><subfield code="z">Mexico, Gulf of</subfield></datafield><datafield ind1=" " ind2=" " tag="450"><subfield code="a">Ocean currents</subfield><subfield code="z">America, Gulf of</subfield></datafield><datafield ind1=" " ind2=" " tag="690"><subfield code="a">sla-lab created local heading based on DEIA Catalog Working Group resolution to keep the term preferred by library community 2025-02-25</subfield></datafield><datafield ind1=" " ind2=" " tag="035"><subfield code="a">(LIBRARY_OF_CONGRESS)98175819020000041</subfield></datafield></record>
<record><leader>00544nz  a2200145n  4500</leader><controlfield tag="005">20250225113025.0</controlfield><controlfield tag="008">130717|| anannbabn          |n ana      </controlfield><controlfield tag="001">98188860307406381</controlfield><datafield ind1=" " ind2=" " tag="010"><subfield code="a">sh2013002058</subfield></datafield><datafield ind1=" " ind2=" " tag="035"><subfield code="a">(DLC)sh2013002058</subfield></datafield><datafield ind1=" " ind2=" " tag="040"><subfield code="a">DLC</subfield><subfield code="b">eng</subfield><subfield code="c">DLC</subfield><subfield code="d">MiU</subfield></datafield><datafield ind1=" " ind2=" " tag="150"><subfield code="a">Mid-ocean ridges</subfield><subfield code="z">Mexico, Gulf of</subfield></datafield><datafield ind1=" " ind2=" " tag="450"><subfield code="a">Mid-ocean ridges</subfield><subfield code="z">America, Gulf of</subfield></datafield><datafield ind1=" " ind2=" " tag="690"><subfield code="a">sla-lab created local heading based on DEIA Catalog Working Group resolution to keep the term preferred by library community 2025-02-25</subfield></datafield><datafield ind1=" " ind2=" " tag="035"><subfield code="a">(LIBRARY_OF_CONGRESS)98210438710000041</subfield></datafield></record>
<record><leader>00729nz  a2200169n  4500</leader><controlfield tag="005">20171103133952.0</controlfield><controlfield tag="008">170906|| anannbabn          |a ana      </controlfield><controlfield tag="001">98188860307506381</controlfield><datafield ind1=" " ind2=" " tag="010"><subfield code="a">sh2017004336</subfield></datafield><datafield ind1=" " ind2=" " tag="035"><subfield code="a">(DLC)sh2017004336</subfield></datafield><datafield ind1=" " ind2=" " tag="040"><subfield code="a">DLC</subfield><subfield code="b">eng</subfield><subfield code="c">DLC</subfield><subfield code="d">MiU</subfield></datafield><datafield ind1=" " ind2=" " tag="151"><subfield code="a">Mexico, Gulf of, Watershed</subfield></datafield><datafield ind1=" " ind2=" " tag="451"><subfield code="a">America, Gulf of, Watershed</subfield></datafield><datafield ind1=" " ind2=" " tag="550"><subfield code="w">g</subfield><subfield code="a">Watersheds</subfield><subfield code="z">Mexico</subfield></datafield><datafield ind1=" " ind2=" " tag="550"><subfield code="w">g</subfield><subfield code="a">Watersheds</subfield><subfield code="z">United States</subfield></datafield><datafield ind1=" " ind2=" " tag="670"><subfield code="a">Work cat.: 2017386748: El proceso de producción cafetalero en la región vertiente del Golfo de México, septiembre 2016:</subfield><subfield code="b">t.p. ([cataloger's translation] The process of coffee production in the watershed of the Gulf of Mexico)</subfield></datafield><datafield ind1=" " ind2=" " tag="670"><subfield code="a">U.S. Fish &amp; Wildlife Service WWW site, viewed Sept. 6, 2017</subfield><subfield code="b">(Gulf of Mexico Watershed)</subfield></datafield><datafield ind1=" " ind2="0" tag="781"><subfield code="z">Mexico, Gulf of, Watershed</subfield></datafield><datafield ind1=" " ind2=" " tag="690"><subfield code="a">sla-lab created local heading based on DEIA Catalog Working Group resolution to keep the term preferred by library community 2025-02-25</subfield></datafield><datafield ind1=" " ind2=" " tag="035"><subfield code="a">(LIBRARY_OF_CONGRESS)988457839400041</subfield></datafield></record>
<record><leader>00703cz  a2200217n  4500</leader><controlfield tag="005">20250225112956.0</controlfield><controlfield tag="008">860211|| anannbabn          |a ana      </controlfield><controlfield tag="001">98188860307706381</controlfield><datafield ind1=" " ind2=" " tag="010"><subfield code="a">sh 85084621</subfield></datafield><datafield ind1=" " ind2=" " tag="035"><subfield code="a">(DLC)sh 85084621</subfield></datafield><datafield ind1=" " ind2=" " tag="040"><subfield code="a">DLC</subfield><subfield code="c">DLC</subfield><subfield code="d">DLC</subfield><subfield code="d">MiU</subfield></datafield><datafield ind1=" " ind2="7" tag="072"><subfield code="a">H 1145.5</subfield><subfield code="2">lcsh</subfield></datafield><datafield ind1=" " ind2=" " tag="151"><subfield code="a">Mexico, Gulf of</subfield></datafield><datafield ind1=" " ind2=" " tag="451"><subfield code="a">Gulf of Mexico</subfield></datafield><datafield ind1=" " ind2=" " tag="451"><subfield code="a">America, Gulf of</subfield></datafield><datafield ind1=" " ind2=" " tag="451"><subfield code="a">Gulf of America</subfield></datafield><datafield ind1=" " ind2=" " tag="550"><subfield code="w">g</subfield><subfield code="a">Bays</subfield><subfield code="z">Mexico</subfield></datafield><datafield ind1=" " ind2=" " tag="550"><subfield code="w">g</subfield><subfield code="a">Bays</subfield><subfield code="z">United States</subfield></datafield><datafield ind1=" " ind2="0" tag="781"><subfield code="z">Mexico, Gulf of</subfield></datafield><datafield ind1=" " ind2=" " tag="690"><subfield code="a">sla-lab created local heading based on DEIA Catalog Working Group resolution to keep the term preferred by library community 2025-02-25</subfield></datafield><datafield ind1=" " ind2=" " tag="035"><subfield code="a">(LIBRARY_OF_CONGRESS)98169244430000041</subfield></datafield></record>
<record><leader>00583nz  a2200157n  4500</leader><controlfield tag="005">20250225112830.0</controlfield><controlfield tag="008">860211|| anannbab|          |n ana |||  </controlfield><controlfield tag="001">98188860307806381</controlfield><datafield ind1=" " ind2=" " tag="010"><subfield code="a">sh 85081270</subfield></datafield><datafield ind1=" " ind2=" " tag="035"><subfield code="a">(DLC) sh 85081270</subfield></datafield><datafield ind1=" " ind2=" " tag="040"><subfield code="a">DLC</subfield><subfield code="c">DLC</subfield><subfield code="d">MiU</subfield></datafield><datafield ind1=" " ind2=" " tag="150"><subfield code="a">Marine sediments</subfield><subfield code="z">Mexico, Gulf of</subfield></datafield><datafield ind1=" " ind2=" " tag="450"><subfield code="a">Marine sediments</subfield><subfield code="z">America, Gulf of</subfield></datafield><datafield ind1=" " ind2=" " tag="681"><subfield code="i">Note under</subfield><subfield code="a">Marine sediments</subfield></datafield><datafield ind1=" " ind2=" " tag="690"><subfield code="a">sla-lab created local heading based on DEIA Catalog Working Group resolution to keep the term preferred by library community 2025-02-25</subfield></datafield><datafield ind1=" " ind2=" " tag="035"><subfield code="a">(LIBRARY_OF_CONGRESS)98171067490000041</subfield></datafield></record>
<record><leader>00571cz  a2200145n  4500</leader><controlfield tag="005">20250225112758.0</controlfield><controlfield tag="008">100623|| anannbabn          |n ana      </controlfield><controlfield tag="001">98188860307906381</controlfield><datafield ind1=" " ind2=" " tag="010"><subfield code="a">sh2010011525</subfield></datafield><datafield ind1=" " ind2=" " tag="035"><subfield code="a">(DLC) sh2010011525</subfield></datafield><datafield ind1=" " ind2=" " tag="040"><subfield code="a">DLC</subfield><subfield code="b">eng</subfield><subfield code="c">DLC</subfield><subfield code="d">MiU</subfield></datafield><datafield ind1=" " ind2=" " tag="150"><subfield code="a">Drilling platforms</subfield><subfield code="x">Accidents</subfield><subfield code="z">Mexico, Gulf of</subfield></datafield><datafield ind1=" " ind2=" " tag="450"><subfield code="a">Drilling platforms</subfield><subfield code="x">Accidents</subfield><subfield code="z">America, Gulf of</subfield></datafield><datafield ind1=" " ind2=" " tag="690"><subfield code="a">sla-lab created local heading based on DEIA Catalog Working Group resolution to keep the term preferred by library community 2025-02-25</subfield></datafield><datafield ind1=" " ind2=" " tag="035"><subfield code="a">(LIBRARY_OF_CONGRESS)98171745090000041</subfield></datafield></record>
<record><leader>00558nz  a2200145n  4500</leader><controlfield tag="005">20250225112725.0</controlfield><controlfield tag="008">961127|| anannbab|          |n ana |||  </controlfield><controlfield tag="001">98188860308006381</controlfield><datafield ind1=" " ind2=" " tag="010"><subfield code="a">sh 96011246</subfield></datafield><datafield ind1=" " ind2=" " tag="035"><subfield code="a">(DLC) sh 96011246</subfield></datafield><datafield ind1=" " ind2=" " tag="040"><subfield code="a">DLC</subfield><subfield code="c">DLC</subfield><subfield code="d">MiU</subfield></datafield><datafield ind1=" " ind2=" " tag="150"><subfield code="a">Cryptoexplosion structures</subfield><subfield code="z">Mexico, Gulf of</subfield></datafield><datafield ind1=" " ind2=" " tag="450"><subfield code="a">Cryptoexplosion structures</subfield><subfield code="z">America, Gulf of</subfield></datafield><datafield ind1=" " ind2=" " tag="690"><subfield code="a">sla-lab created local heading based on DEIA Catalog Working Group resolution to keep the term preferred by library community 2025-02-25</subfield></datafield><datafield ind1=" " ind2=" " tag="035"><subfield code="a">(LIBRARY_OF_CONGRESS)98171136640000041</subfield></datafield></record>
<record><leader>00558nz  a2200145n  4500</leader><controlfield tag="005">20250225112643.0</controlfield><controlfield tag="008">130717|| anannbabn          |n ana      </controlfield><controlfield tag="001">98188860308106381</controlfield><datafield ind1=" " ind2=" " tag="010"><subfield code="a">sh2013002057</subfield></datafield><datafield ind1=" " ind2=" " tag="035"><subfield code="a">(DLC)sh2013002057</subfield></datafield><datafield ind1=" " ind2=" " tag="040"><subfield code="a">DLC</subfield><subfield code="b">eng</subfield><subfield code="c">DLC</subfield><subfield code="d">MiU</subfield></datafield><datafield ind1=" " ind2=" " tag="150"><subfield code="a">Coral reefs and islands</subfield><subfield code="z">Mexico, Gulf of</subfield></datafield><datafield ind1=" " ind2=" " tag="450"><subfield code="a">Coral reefs and islands</subfield><subfield code="z">America, Gulf of</subfield></datafield><datafield ind1=" " ind2=" " tag="690"><subfield code="a">sla-lab created local heading based on DEIA Catalog Working Group resolution to keep the term preferred by library community 2025-02-25</subfield></datafield><datafield ind1=" " ind2=" " tag="035"><subfield code="a">(LIBRARY_OF_CONGRESS)98210438720000041</subfield></datafield></record>
<record><leader>00542nz  a2200145n  4500</leader><controlfield tag="005">20250225112617.0</controlfield><controlfield tag="008">951222|| anannbab|          |n ana |||  </controlfield><controlfield tag="001">98188860308306381</controlfield><datafield ind1=" " ind2=" " tag="010"><subfield code="a">sh 95010829</subfield></datafield><datafield ind1=" " ind2=" " tag="035"><subfield code="a">(DLC) sh 95010829</subfield></datafield><datafield ind1=" " ind2=" " tag="040"><subfield code="a">DLC</subfield><subfield code="c">DLC</subfield><subfield code="d">MiU</subfield></datafield><datafield ind1=" " ind2=" " tag="150"><subfield code="a">Continental slopes</subfield><subfield code="z">Mexico, Gulf of</subfield></datafield><datafield ind1=" " ind2=" " tag="450"><subfield code="a">Continental slopes</subfield><subfield code="z">America, Gulf of</subfield></datafield><datafield ind1=" " ind2=" " tag="690"><subfield code="a">sla-lab created local heading based on DEIA Catalog Working Group resolution to keep the term preferred by library community 2025-02-25</subfield></datafield><datafield ind1=" " ind2=" " tag="035"><subfield code="a">(LIBRARY_OF_CONGRESS)98172603570000041</subfield></datafield></record>
<record><leader>00645cz  a2200157n  4500</leader><controlfield tag="005">20250225112537.0</controlfield><controlfield tag="008">090818|| anannbabn          |n ana      </controlfield><controlfield tag="001">98188860308406381</controlfield><datafield ind1=" " ind2=" " tag="010"><subfield code="a">sh2009121725</subfield></datafield><datafield ind1=" " ind2=" " tag="035"><subfield code="a">(DLC)sh2009121725</subfield></datafield><datafield ind1=" " ind2=" " tag="040"><subfield code="a">DLC</subfield><subfield code="b">eng</subfield><subfield code="c">DLC</subfield><subfield code="d">MiU</subfield></datafield><datafield ind1=" " ind2=" " tag="150"><subfield code="a">Continental shelf</subfield><subfield code="z">Mexico, Gulf of</subfield></datafield><datafield ind1=" " ind2=" " tag="450"><subfield code="a">Continental shelf</subfield><subfield code="z">America, Gulf of</subfield></datafield><datafield ind1=" " ind2=" " tag="670"><subfield code="a">Work cat.: Fate and effects of nearshore discharges of OCS produced waters, [1991]</subfield></datafield><datafield ind1=" " ind2=" " tag="690"><subfield code="a">sla-lab created local heading based on DEIA Catalog Working Group resolution to keep the term preferred by library community 2025-02-25</subfield></datafield><datafield ind1=" " ind2=" " tag="035"><subfield code="a">(LIBRARY_OF_CONGRESS)98171073650000041</subfield></datafield></record>
<record><leader>00915cz  a2200205n  4500</leader><controlfield tag="005">20250225112514.0</controlfield><controlfield tag="008">951222|| anannbabn          |a ana     c</controlfield><controlfield tag="001">98188860308606381</controlfield><datafield ind1=" " ind2=" " tag="010"><subfield code="a">sh 95010828</subfield></datafield><datafield ind1=" " ind2=" " tag="035"><subfield code="a">(DLC) sh 95010828</subfield></datafield><datafield ind1=" " ind2=" " tag="040"><subfield code="a">DGPO</subfield><subfield code="c">DLC</subfield><subfield code="d">DLC</subfield><subfield code="d">MiU</subfield></datafield><datafield ind1=" " ind2=" " tag="151"><subfield code="a">Central Slope (Gulf of Mexico)</subfield></datafield><datafield ind1=" " ind2=" " tag="451"><subfield code="a">Central Slope (Gulf of America)</subfield></datafield><datafield ind1=" " ind2=" " tag="550"><subfield code="w">g</subfield><subfield code="a">Continental slopes</subfield><subfield code="z">Mexico, Gulf of</subfield></datafield><datafield ind1=" " ind2=" " tag="670"><subfield code="a">Work cat.: U.S. National Ocean Service. Bathymetric map, Gulf of Mexico, Central Slope, 1991:</subfield><subfield code="b">map recto (Central Slope, Gulf of Mexico)</subfield></datafield><datafield ind1=" " ind2=" " tag="670"><subfield code="a">BGN gaz. of undersea features, 1990</subfield><subfield code="b">(Central Slope, slope)</subfield></datafield><datafield ind1=" " ind2=" " tag="675"><subfield code="a">Nat. Geog. atlas;</subfield><subfield code="a">Web. geog.</subfield></datafield><datafield ind1=" " ind2="0" tag="781"><subfield code="z">Central Slope (Gulf of Mexico)</subfield></datafield><datafield ind1=" " ind2=" " tag="690"><subfield code="a">sla-lab created local heading based on DEIA Catalog Working Group resolution to keep the term preferred by library community 2025-02-25</subfield></datafield><datafield ind1=" " ind2=" " tag="035"><subfield code="a">(LIBRARY_OF_CONGRESS)98172603520000041</subfield></datafield></record>
<record><leader>00703cz  a2200157n  4500</leader><controlfield tag="005">20250225112428.0</controlfield><controlfield tag="008">091210|| anannbabn          |n ana      </controlfield><controlfield tag="001">98188860308706381</controlfield><datafield ind1=" " ind2=" " tag="010"><subfield code="a">sh2009010707</subfield></datafield><datafield ind1=" " ind2=" " tag="035"><subfield code="a">(DLC)sh2009010707</subfield></datafield><datafield ind1=" " ind2=" " tag="040"><subfield code="a">DLC</subfield><subfield code="b">eng</subfield><subfield code="c">DLC</subfield><subfield code="d">MiU</subfield></datafield><datafield ind1=" " ind2=" " tag="150"><subfield code="a">Bottlenose dolphin</subfield><subfield code="x">Behavior</subfield><subfield code="z">Mexico, Gulf of</subfield></datafield><datafield ind1=" " ind2=" " tag="450"><subfield code="a">Bottlenose dolphin</subfield><subfield code="x">Behavior</subfield><subfield code="z">America, Gulf of</subfield></datafield><datafield ind1=" " ind2=" " tag="670"><subfield code="a">Work cat.: Caldwell, Melba C. Observations on captive and wild Atlantic bottlenosed dolphins, Tursiops truncatus, 1965</subfield></datafield><datafield ind1=" " ind2=" " tag="690"><subfield code="a">sla-lab created local heading based on DEIA Catalog Working Group resolution to keep the term preferred by library community 2025-02-25</subfield></datafield><datafield ind1=" " ind2=" " tag="035"><subfield code="a">(LIBRARY_OF_CONGRESS)98169175220000041</subfield></datafield></record>
<record><leader>00546nz  a2200145n  4500</leader><controlfield tag="005">20250225112245.0</controlfield><controlfield tag="008">910122|| anannbab|          |n ana |||  </controlfield><controlfield tag="001">98188860308806381</controlfield><datafield ind1=" " ind2=" " tag="010"><subfield code="a">sh 91000336</subfield></datafield><datafield ind1=" " ind2=" " tag="035"><subfield code="a">(DLC) sh 91000336</subfield></datafield><datafield ind1=" " ind2=" " tag="040"><subfield code="a">DLC</subfield><subfield code="c">DLC</subfield><subfield code="d">MiU</subfield></datafield><datafield ind1=" " ind2="0" tag="150"><subfield code="a">Banks (Oceanography)</subfield><subfield code="z">Mexico, Gulf of</subfield></datafield><datafield ind1=" " ind2="0" tag="450"><subfield code="a">Banks (Oceanography)</subfield><subfield code="z">America, Gulf of</subfield></datafield><datafield ind1=" " ind2=" " tag="690"><subfield code="a">sla-lab created local heading based on DEIA Catalog Working Group resolution to keep the term preferred by library community 2025-02-25</subfield></datafield><datafield ind1=" " ind2=" " tag="035"><subfield code="a">(LIBRARY_OF_CONGRESS)98172068840000041</subfield></datafield></record>
<record><leader>04817cz  a2200793n  4500</leader><controlfield tag="005">20250225112256.0</controlfield><controlfield tag="008">860211|| anannbabn          |a ana      </controlfield><controlfield tag="001">98188860309506381</controlfield><datafield ind1=" " ind2=" " tag="010"><subfield code="a">sh 85082617</subfield></datafield><datafield ind1=" " ind2=" " tag="034"><subfield code="d">W1510027</subfield><subfield code="e">W1510027</subfield><subfield code="f">N0630410</subfield><subfield code="g">N0630410</subfield><subfield code="2">geonames</subfield></datafield><datafield ind1=" " ind2=" " tag="035"><subfield code="a">(DLC)sh 85082617</subfield></datafield><datafield ind1=" " ind2=" " tag="040"><subfield code="a">DLC</subfield><subfield code="c">DLC</subfield><subfield code="d">DLC</subfield><subfield code="d">MiU</subfield></datafield><datafield ind1=" " ind2=" " tag="151"><subfield code="a">Denali, Mount (Alaska)</subfield></datafield><datafield ind1=" " ind2=" " tag="451"><subfield code="a">Bolshoy Mountain (Alaska)</subfield></datafield><datafield ind1=" " ind2=" " tag="451"><subfield code="a">Bulshaia Gora (Alaska)</subfield></datafield><datafield ind1=" " ind2=" " tag="451"><subfield code="a">Bulshaya Gora (Alaska)</subfield></datafield><datafield ind1=" " ind2=" " tag="451"><subfield code="a">Bulshoe (Alaska)</subfield></datafield><datafield ind1=" " ind2=" " tag="451"><subfield code="a">Churchill Peaks (Alaska)</subfield></datafield><datafield ind1=" " ind2=" " tag="451"><subfield code="a">Deenaalee Mountain (Alaska)</subfield></datafield><datafield ind1=" " ind2=" " tag="451"><subfield code="a">Deenadhee (Alaska)</subfield></datafield><datafield ind1=" " ind2=" " tag="451"><subfield code="a">Deenadheet (Alaska)</subfield></datafield><datafield ind1=" " ind2=" " tag="451"><subfield code="a">Deenalee (Alaska)</subfield></datafield><datafield ind1=" " ind2=" " tag="451"><subfield code="a">Deghilaay Ce'e (Alaska)</subfield></datafield><datafield ind1=" " ind2=" " tag="451"><subfield code="a">Deghilaay Ke'e (Alaska)</subfield></datafield><datafield ind1=" " ind2=" " tag="451"><subfield code="a">Delaykah (Alaska)</subfield></datafield><datafield ind1=" " ind2=" " tag="451"><subfield code="a">Denadhe (Alaska)</subfield></datafield><datafield ind1=" " ind2=" " tag="451"><subfield code="a">Denagadh (Alaska)</subfield></datafield><datafield ind1=" " ind2=" " tag="451"><subfield code="a">Denaze (Alaska)</subfield></datafield><datafield ind1=" " ind2=" " tag="451"><subfield code="a">Dengadh (Alaska)</subfield></datafield><datafield ind1=" " ind2=" " tag="451"><subfield code="a">Dengadhe (Alaska)</subfield></datafield><datafield ind1=" " ind2=" " tag="451"><subfield code="a">Dengadhi (Alaska)</subfield></datafield><datafield ind1=" " ind2=" " tag="451"><subfield code="a">Dengadhiy (Alaska)</subfield></datafield><datafield ind1=" " ind2=" " tag="451"><subfield code="a">Densmore's Mountain (Alaska)</subfield></datafield><datafield ind1=" " ind2=" " tag="451"><subfield code="a">Densmores Peak (Alaska)</subfield></datafield><datafield ind1=" " ind2=" " tag="451"><subfield code="a">Dghelaay Ce'e (Alaska)</subfield></datafield><datafield ind1=" " ind2=" " tag="451"><subfield code="a">Dghelaay Ke'e (Alaska)</subfield></datafield><datafield ind1=" " ind2=" " tag="451"><subfield code="a">Dghelay Ka'a (Alaska)</subfield></datafield><datafield ind1=" " ind2=" " tag="451"><subfield code="a">Dghili Ka'a (Alaska)</subfield></datafield><datafield ind1=" " ind2=" " tag="451"><subfield code="a">Diinaadhi (Alaska)</subfield></datafield><datafield ind1=" " ind2=" " tag="451"><subfield code="a">Diinaadhii (Alaska)</subfield></datafield><datafield ind1=" " ind2=" " tag="451"><subfield code="a">Diinaadhiit (Alaska)</subfield></datafield><datafield ind1=" " ind2=" " tag="451"><subfield code="a">Diinaalii (Alaska)</subfield></datafield><datafield ind1=" " ind2=" " tag="451"><subfield code="a">Diinaazii (Alaska)</subfield></datafield><datafield ind1=" " ind2=" " tag="451"><subfield code="a">Diineezi (Alaska)</subfield></datafield><datafield ind1=" " ind2=" " tag="451"><subfield code="a">Din-al-ee (Alaska : Mount Denali)</subfield></datafield><datafield ind1=" " ind2=" " tag="451"><subfield code="a">Din-az-ee (Alaska : Mount Denali)</subfield></datafield><datafield ind1=" " ind2=" " tag="451"><subfield code="a">Doleika (Alaska)</subfield></datafield><datafield ind1=" " ind2=" " tag="451"><subfield code="a">Doleyka (Alaska)</subfield></datafield><datafield ind1=" " ind2=" " tag="451"><subfield code="w">nne</subfield><subfield code="a">McKinley, Mount (Alaska)</subfield></datafield><datafield ind1=" " ind2=" " tag="451"><subfield code="a">Mount Denali (Alaska)</subfield></datafield><datafield ind1=" " ind2=" " tag="451"><subfield code="a">Mount Doleika (Alaska)</subfield></datafield><datafield ind1=" " ind2=" " tag="451"><subfield code="a">Mount McKinley (Alaska)</subfield></datafield><datafield ind1=" " ind2=" " tag="451"><subfield code="a">North Peak (Alaska : Mount Denali)</subfield></datafield><datafield ind1=" " ind2=" " tag="451"><subfield code="a">South Peak (Alaska : Mount Denali)</subfield></datafield><datafield ind1=" " ind2=" " tag="451"><subfield code="a">Tenada (Alaska)</subfield></datafield><datafield ind1=" " ind2=" " tag="451"><subfield code="a">Tenda (Alaska)</subfield></datafield><datafield ind1=" " ind2=" " tag="451"><subfield code="a">Tennaly (Alaska)</subfield></datafield><datafield ind1=" " ind2=" " tag="451"><subfield code="a">To-lah-gah (Alaska)</subfield></datafield><datafield ind1=" " ind2=" " tag="451"><subfield code="a">Traleika (Alaska : Mount Denali)</subfield></datafield><datafield ind1=" " ind2=" " tag="451"><subfield code="a">Traleyka (Alaska)</subfield></datafield><datafield ind1=" " ind2=" " tag="551"><subfield code="w">g</subfield><subfield code="a">Alaska Range (Alaska)</subfield></datafield><datafield ind1=" " ind2=" " tag="550"><subfield code="w">g</subfield><subfield code="a">Mountains</subfield><subfield code="z">Alaska</subfield></datafield><datafield ind1=" " ind2=" " tag="670"><subfield code="a">GeoNames [algorithmically matched]</subfield><subfield code="b">summit; 63°04ʹ10ʺN 151°00ʹ27ʺW</subfield></datafield><datafield ind1=" " ind2=" " tag="670"><subfield code="a">GNIS, Aug. 31, 2015:</subfield><subfield code="b">(Denali; summit in Denali County, Alaska; variant names: Bolshoy; Bulshaia Gora; Bulshaya Gora; Bulshoe; Churchill Peaks; Deenaalee; Deenadhee; Deenadheet; Deenalee; Deghilaay Ce'e; Deghilaay Ke'e; Delaykah; Denadhe; Denagadh; Denaze; Dengadh; Dengadhe; Dengadhi; Dengadhiy; Densmore's Mountain; Densmores Peak; Dghelaay Ce'e; Dghelaay Ke'e; Dghelay Ka'a; Dghili Ka'a; Diinaadhi; Diinaadhii; Diinaadhiit; Diinaalii; Diinaazii; Diineezi; Din-al-ee; Din-az-ee; Doleika; Doleyka; Mount Denali; Mount Doleika; Mount McKinley; North Peak; North Peak Mount McKinley; South Peak; South Peak Mount McKinley; Tenada; Tenda; Tennaly; To-lah-gah; Traleika; Traleyka; Denali also name of ppl and several other jurisdictions in Alaska; Bolshoy also name of several islands; Deenaalee also name of lake; Din-al-ee and Din-az-ee also variant names for Mount Foraker in Denali County; Traleika also name of summit in "Alaska Range near Mount McKinley" [no county listed]; North Peak and South Peak also names for other summits in other counties in Alaska)</subfield></datafield><datafield ind1=" " ind2=" " tag="670"><subfield code="a">Washington Post online, Aug. 31, 2015:</subfield><subfield code="b">(article: Obama will rename the highest U.S. peak, dropping McKinley for Denali; President Obama in Anchorage on Monday will announce the renaming of Mount McKinley, honoring the 25th president, to Mount Denali, an Athabascan name used by generations of Alaska Natives that means "the great one.")</subfield></datafield><datafield ind1=" " ind2=" " tag="670"><subfield code="a">Columbia gazetteer online, Aug. 31, 2015:</subfield><subfield code="b">(McKinley, Mount or Denali (=the great one), mountain (20,320 ft/6,194 m), S central Alaska, in the Alaska Range; 63°04ʹN 151°00ʹW. Highest point in North America. McKinley features two main peaks: the higher is South Peak (20,320 ft/6,194 m) and North Peak (19,470 ft/5,934 m); the two together have sometimes been known as the Churchhill Peaks. Other notable peaks on the mountain are South Buttress (15,885 ft/4,842 m), East Buttress (14,730 ft/4,490 m), and Browne Tower (14,530 ft/4,429m). Permanent snowfields cover more than half the mountain and feed numerous glaciers. Mount McKinley was first scaled successfully by the American explorer Hudson Stuck in 1913. It is included in Denali National Park and Preserve.)</subfield></datafield><datafield ind1=" " ind2=" " tag="690"><subfield code="a">sla-lab created local heading based on DEIA Catalog Working Group resolution to keep the term preferred by Alaska legislature and indigenous peoples 2025-02-25</subfield></datafield><datafield ind1=" " ind2="0" tag="781"><subfield code="z">Alaska</subfield><subfield code="z">Denali, Mount</subfield></datafield><datafield ind1=" " ind2=" " tag="035"><subfield code="a">(LIBRARY_OF_CONGRESS)98170841570000041</subfield></datafield></record>
